MANIFEST.in
README.rst
setup.py
google/__init__.py
google/logging/__init__.py
google/logging/v2/__init__.py
google/logging/v2/log_entry_pb2.py
google/logging/v2/logging_config_pb2.py
google/logging/v2/logging_metrics_pb2.py
google/logging/v2/logging_pb2.py
grpc_google_logging_v2.egg-info/PKG-INFO
grpc_google_logging_v2.egg-info/SOURCES.txt
grpc_google_logging_v2.egg-info/dependency_links.txt
grpc_google_logging_v2.egg-info/namespace_packages.txt
grpc_google_logging_v2.egg-info/requires.txt
grpc_google_logging_v2.egg-info/top_level.txt